{
  "errorCode": 0,
  "msg": "登录成功",
  "data": {
    "token": "U9yWTmyCs_wSRAF1drXqno-oeqVeE992_1760284818",
    "user": {
      "id": 134722,
      "nickname": "",
      "mobile": "",
      "email": "37f9vo1r@snapbx.com",
      "gender": "男",
      "location": "",
      "birthday": null,
      "birth_sign": "",
      "avatar": "",
      "code": "wHGyI2",
      "total_money": "0.00",
      "expire_at": "2025-10-14 00:00:17",
      "is_vip": true
    }
  },
  "upload_time": "2025-10-12T16:00:20.228Z",
  "email": "37f9vo1r@snapbx.com"
}