{
  "errorCode": 0,
  "msg": "登录成功",
  "data": {
    "token": "T9GuZ2QZNbLQ_LUQ5SJcnzeZbVkR8xO0_1758232817",
    "user": {
      "id": 131333,
      "nickname": "",
      "mobile": "",
      "email": "ekl5loxj@temailz.com",
      "gender": "男",
      "location": "",
      "birthday": null,
      "birth_sign": "",
      "avatar": "",
      "code": "m9CKny",
      "total_money": "0.00",
      "expire_at": "2025-09-20 06:00:16",
      "is_vip": true
    }
  },
  "upload_time": "2025-09-18T22:00:18.873Z",
  "email": "ekl5loxj@temailz.com"
}