{
  "vipendtime": "2026-01-01 08:00:03",
  "cookie": "user_type=0; 1&_device=iPhone&5484ec4b-d4b2-4af4-970f-c8344e136a00&2.25.1; x-intl-mulehorse-bucketIds=%2C; net-mode=WIFI; channel=ios-appstore; country_id=1; idfa=7378f3e0-2b4e-49b9-ae0b-542c8e285f4b; domain=apisg.himalaya.com; appsflyer_id=1767214800-1111111; locale=zh_CN; path=/; 1&_token=10007120048&b214aa2207508042910b8ef053f3bdd2f763; location=sg; impl=com.ximalaya.xmlyi; x-abtest-bucketIds=; JSESSIONID=",
  "email": "606091307@gmail.com",
  "uid": 10007120048,
  "token": "b214aa2207508042910b8ef053f3bdd2f763"
}