{
  "vipendtime": "2026-01-28 19:00:04",
  "cookie": "user_type=0; 1&_device=iPhone&75af1f1a-7088-488e-a388-9a2cdd48d8be&2.25.1; x-intl-mulehorse-bucketIds=%2C; net-mode=WIFI; channel=ios-appstore; country_id=1; idfa=01f1e3e7-6431-4776-bc5a-142bdea8cacb; domain=apisg.himalaya.com; appsflyer_id=1769587201-1111111; locale=zh_CN; path=/; 1&_token=10007151140&7ec2f9e801670045c4086e6097bd771d940b; location=sg; impl=com.ximalaya.xmlyi; x-abtest-bucketIds=; JSESSIONID=",
  "email": "668514767@gmail.com",
  "uid": 10007151140,
  "token": "7ec2f9e801670045c4086e6097bd771d940b"
}