{
  "vipendtime": "2026-03-05 02:00:08",
  "cookie": "user_type=0; 1&_device=iPhone&45d55f77-99a2-418b-a813-3fbbd2df779d&2.25.1; x-intl-mulehorse-bucketIds=%2C; net-mode=WIFI; channel=ios-appstore; country_id=1; idfa=3ab29bc3-bd5f-4c7b-a492-86c74e71faea; domain=apisg.himalaya.com; appsflyer_id=1772636401-1111111; locale=zh_CN; path=/; 1&_token=10007187643&7f57855c085f804cb709b98070cf42be9b3b; location=sg; impl=com.ximalaya.xmlyi; x-abtest-bucketIds=; JSESSIONID=",
  "email": "64364030@gmail.com",
  "uid": 10007187643,
  "token": "7f57855c085f804cb709b98070cf42be9b3b"
}