{
  "vipendtime": "2025-11-01 09:00:08",
  "cookie": "user_type=0; 1&_device=iPhone&ca00cf05-7da9-4da0-9802-9a9b94a62d6c&2.25.1; x-intl-mulehorse-bucketIds=%2C; net-mode=WIFI; channel=ios-appstore; country_id=1; idfa=11c68143-1ab3-44ad-892c-b9bdbed07c6d; domain=apisg.himalaya.com; appsflyer_id=1761948000-1111111; locale=zh_CN; path=/; 1&_token=10007020989&d8bc28d10ffe60411f0872009d229f20a39b; location=sg; impl=com.ximalaya.xmlyi; x-abtest-bucketIds=; JSESSIONID=",
  "email": "412665246@gmail.com",
  "uid": 10007020989,
  "token": "d8bc28d10ffe60411f0872009d229f20a39b"
}