{
  "vipendtime": "2025-11-06 12:00:04",
  "cookie": "user_type=0; 1&_device=iPhone&1fd9e349-0c53-4002-82b8-7b8b1834d12f&2.25.1; x-intl-mulehorse-bucketIds=%2C; net-mode=WIFI; channel=ios-appstore; country_id=1; idfa=84a12f69-d2c4-4e91-92c5-6640427aa1ec; domain=apisg.himalaya.com; appsflyer_id=1762390801-1111111; locale=zh_CN; path=/; 1&_token=10007030262&66e3894f0d93c0473508c2908d91ebc15784; location=sg; impl=com.ximalaya.xmlyi; x-abtest-bucketIds=; JSESSIONID=",
  "email": "802122967@gmail.com",
  "uid": 10007030262,
  "token": "66e3894f0d93c0473508c2908d91ebc15784"
}