{
  "vipendtime": "2025-10-03 16:48:44",
  "cookie": "user_type=0; 1&_device=iPhone&dd3d9108-7c29-4673-94e0-32745b20ca22&2.25.1; x-intl-mulehorse-bucketIds=%2C; net-mode=WIFI; channel=ios-appstore; country_id=1; idfa=88a6f507-3337-4b23-8801-aab0691d6e4c; domain=apisg.himalaya.com; appsflyer_id=1759470522-1111111; locale=zh_CN; path=/; 1&_token=10006972608&9c7b95a60129d04e740a6c80f3c2639eab31; location=sg; impl=com.ximalaya.xmlyi; x-abtest-bucketIds=; JSESSIONID=",
  "email": "370241869@gmail.com",
  "uid": 10006972608,
  "token": "9c7b95a60129d04e740a6c80f3c2639eab31",
  "member_minutes": 180,
  "upload_time": "2025-10-03T05:48:44.551Z"
}