{
  "vipendtime": "2026-02-19 13:00:22",
  "cookie": "user_type=0; 1&_device=iPhone&dbc4eeee-0993-4f82-91db-f595f8ef0c39&2.25.1; x-intl-mulehorse-bucketIds=%2C; net-mode=WIFI; channel=ios-appstore; country_id=1; idfa=0602d8a6-9c3f-4fdb-9a4c-5606dd45c767; domain=apisg.himalaya.com; appsflyer_id=1771466401-1111111; locale=zh_CN; path=/; 1&_token=10007172224&220cb521089f504b050bf810c29a6225cc6d; location=sg; impl=com.ximalaya.xmlyi; x-abtest-bucketIds=; JSESSIONID=",
  "email": "385761516@gmail.com",
  "uid": 10007172224,
  "token": "220cb521089f504b050bf810c29a6225cc6d"
}