{
  "vipendtime": "2025-12-16 16:00:04",
  "cookie": "user_type=0; 1&_device=iPhone&db0c0fc3-9462-4fc0-9158-cb9422349c70&2.25.1; x-intl-mulehorse-bucketIds=%2C; net-mode=WIFI; channel=ios-appstore; country_id=1; idfa=30dc9927-9816-45d2-89f2-23f424e0c25f; domain=apisg.himalaya.com; appsflyer_id=1765861200-1111111; locale=zh_CN; path=/; 1&_token=10007102322&3b2ddb520020e04a810bea70ca89ab49114c; location=sg; impl=com.ximalaya.xmlyi; x-abtest-bucketIds=; JSESSIONID=",
  "email": "300804697@gmail.com",
  "uid": 10007102322,
  "token": "3b2ddb520020e04a810bea70ca89ab49114c"
}