{
  "vipendtime": "2026-06-14 12:00:03",
  "cookie": "user_type=0; 1&_device=iPhone&6fda0b22-bd60-4960-a941-89f386342e20&2.25.1; x-intl-mulehorse-bucketIds=%2C; net-mode=WIFI; channel=ios-appstore; country_id=1; idfa=c9d4db2c-a46b-4d0b-847d-c59953b9944d; domain=apisg.himalaya.com; appsflyer_id=1781398800-1111111; locale=zh_CN; path=/; 1&_token=10007319094&cdb8c16a03bf9047ec0a3560c217456830fd; location=sg; impl=com.ximalaya.xmlyi; x-abtest-bucketIds=; JSESSIONID=",
  "email": "455136369@gmail.com",
  "uid": 10007319094,
  "token": "cdb8c16a03bf9047ec0a3560c217456830fd"
}