{
  "vipendtime": "2026-06-12 04:00:04",
  "cookie": "user_type=0; 1&_device=iPhone&436d4e30-9765-4d96-997c-831043ce8fff&2.25.1; x-intl-mulehorse-bucketIds=%2C; net-mode=WIFI; channel=ios-appstore; country_id=1; idfa=ce1f3584-35d4-4db3-8219-89ae86e821c7; domain=apisg.himalaya.com; appsflyer_id=1781197200-1111111; locale=zh_CN; path=/; 1&_token=10007316602&365eeeea08b3104e0608637053f566eba349; location=sg; impl=com.ximalaya.xmlyi; x-abtest-bucketIds=; JSESSIONID=",
  "email": "420486659@gmail.com",
  "uid": 10007316602,
  "token": "365eeeea08b3104e0608637053f566eba349"
}