{
  "vipendtime": "2026-06-13 19:00:05",
  "cookie": "user_type=0; 1&_device=iPhone&b557fb5d-b613-4f25-bf6b-4d61ca334061&2.25.1; x-intl-mulehorse-bucketIds=%2C; net-mode=WIFI; channel=ios-appstore; country_id=1; idfa=1c734138-87ea-48e9-9605-392aa469a247; domain=apisg.himalaya.com; appsflyer_id=1781337600-1111111; locale=zh_CN; path=/; 1&_token=10007318256&bada577a069a804af7094f60225440f347ef; location=sg; impl=com.ximalaya.xmlyi; x-abtest-bucketIds=; JSESSIONID=",
  "email": "268695328@gmail.com",
  "uid": 10007318256,
  "token": "bada577a069a804af7094f60225440f347ef"
}