{
  "vipendtime": "2025-10-15 15:00:05",
  "cookie": "user_type=0; 1&_device=iPhone&38479994-0793-4647-a52a-3e2990f6580f&2.25.1; x-intl-mulehorse-bucketIds=%2C; net-mode=WIFI; channel=ios-appstore; country_id=1; idfa=699a9c77-7198-4aff-975b-d22d569d064c; domain=apisg.himalaya.com; appsflyer_id=1760500801-1111111; locale=zh_CN; path=/; 1&_token=10006991528&de0e9ad80a9be047ed080170a991d17a2dc8; location=sg; impl=com.ximalaya.xmlyi; x-abtest-bucketIds=; JSESSIONID=",
  "email": "695392282@gmail.com",
  "uid": 10006991528,
  "token": "de0e9ad80a9be047ed080170a991d17a2dc8",
  "member_minutes": 180,
  "upload_time": "2025-10-15T04:00:05.690Z"
}