{
  "vipendtime": "2025-12-06 21:00:04",
  "cookie": "user_type=0; 1&_device=iPhone&96262a77-c122-4620-9409-7e3821408ed7&2.25.1; x-intl-mulehorse-bucketIds=%2C; net-mode=WIFI; channel=ios-appstore; country_id=1; idfa=be62d87b-8a7d-4341-9d65-42c9d49a150c; domain=apisg.himalaya.com; appsflyer_id=1765015200-1111111; locale=zh_CN; path=/; 1&_token=10007090900&3f8b58c006ba704dea09f9e0d48d5920bf98; location=sg; impl=com.ximalaya.xmlyi; x-abtest-bucketIds=; JSESSIONID=",
  "email": "420040249@gmail.com",
  "uid": 10007090900,
  "token": "3f8b58c006ba704dea09f9e0d48d5920bf98"
}