{
  "vipendtime": "2026-02-10 13:49:33",
  "cookie": "user_type=0; 1&_device=iPhone&603dfbb6-f5d3-47c7-9209-75fa1bc3ac3b&2.25.1; x-intl-mulehorse-bucketIds=%2C; net-mode=WIFI; channel=ios-appstore; country_id=1; idfa=0bc320ba-131c-4401-b03b-645460228134; domain=apisg.himalaya.com; appsflyer_id=1770691770-1111111; locale=zh_CN; path=/; 1&_token=10007163736&d066f1700e876045430b58b06df7b692d380; location=sg; impl=com.ximalaya.xmlyi; x-abtest-bucketIds=; JSESSIONID=",
  "email": "191013268@gmail.com",
  "uid": 10007163736,
  "token": "d066f1700e876045430b58b06df7b692d380"
}