{
  "vipendtime": "2026-03-11 14:00:22",
  "cookie": "user_type=0; 1&_device=iPhone&a0e4dcda-415c-44d6-bea2-46f4bc582c42&2.25.1; x-intl-mulehorse-bucketIds=%2C; net-mode=WIFI; channel=ios-appstore; country_id=1; idfa=d14b782d-bb95-4c48-8104-53e112d14ede; domain=apisg.himalaya.com; appsflyer_id=1773198000-1111111; locale=zh_CN; path=/; 1&_token=10007194822&e7f0b2f20acec04b430ae970740641c2c655; location=sg; impl=com.ximalaya.xmlyi; x-abtest-bucketIds=; JSESSIONID=",
  "email": "880604902@gmail.com",
  "uid": 10007194822,
  "token": "e7f0b2f20acec04b430ae970740641c2c655"
}