{
  "vipendtime": "2025-09-30 15:00:03",
  "cookie": "user_type=0; 1&_device=iPhone&9338d655-bde3-4653-9c81-077a3e5fe80c&2.25.1; x-intl-mulehorse-bucketIds=%2C; net-mode=WIFI; channel=ios-appstore; country_id=1; idfa=afb87187-7732-4dd2-a85f-f0ab70615804; domain=apisg.himalaya.com; appsflyer_id=1759204800-1111111; locale=zh_CN; path=/; 1&_token=10006967642&43f8f96b080d50499b0923b0489827052b48; location=sg; impl=com.ximalaya.xmlyi; x-abtest-bucketIds=; JSESSIONID=",
  "email": "975024646@gmail.com",
  "uid": 10006967642,
  "token": "43f8f96b080d50499b0923b0489827052b48",
  "member_minutes": 180,
  "upload_time": "2025-09-30T04:00:03.006Z"
}