{
  "vipendtime": "2026-01-06 10:00:10",
  "cookie": "user_type=0; 1&_device=iPhone&b3fa23ae-1ea0-405c-8ee5-d46a3274f199&2.25.1; x-intl-mulehorse-bucketIds=%2C; net-mode=WIFI; channel=ios-appstore; country_id=1; idfa=fba3b82d-9cd0-4d53-a008-05dca46666c3; domain=apisg.himalaya.com; appsflyer_id=1767654001-1111111; locale=zh_CN; path=/; 1&_token=10007126249&ae316ab403d0d04ea70adec0b6213a135a9c; location=sg; impl=com.ximalaya.xmlyi; x-abtest-bucketIds=; JSESSIONID=",
  "email": "154603662@gmail.com",
  "uid": 10007126249,
  "token": "ae316ab403d0d04ea70adec0b6213a135a9c"
}