{
  "vipendtime": "2025-12-30 02:00:12",
  "cookie": "user_type=0; 1&_device=iPhone&0134b959-ff38-484e-8bcc-70893d06820e&2.25.1; x-intl-mulehorse-bucketIds=%2C; net-mode=WIFI; channel=ios-appstore; country_id=1; idfa=14c170ff-99bb-4e14-b3ba-79dbdfd69d0d; domain=apisg.himalaya.com; appsflyer_id=1767020400-1111111; locale=zh_CN; path=/; 1&_token=10007117625&480273860c7b104a9809f100c86ce7183ae0; location=sg; impl=com.ximalaya.xmlyi; x-abtest-bucketIds=; JSESSIONID=",
  "email": "540580887@gmail.com",
  "uid": 10007117625,
  "token": "480273860c7b104a9809f100c86ce7183ae0"
}