{
  "vipendtime": "2025-12-23 19:00:04",
  "cookie": "user_type=0; 1&_device=iPhone&a61b0037-345b-4449-8dc4-bf81962b8968&2.25.1; x-intl-mulehorse-bucketIds=%2C; net-mode=WIFI; channel=ios-appstore; country_id=1; idfa=dc972098-702c-4eec-92f4-f6f594cd2159; domain=apisg.himalaya.com; appsflyer_id=1766476800-1111111; locale=zh_CN; path=/; 1&_token=10007109776&dbd7419b0c4c80455309db302b102f4fe98f; location=sg; impl=com.ximalaya.xmlyi; x-abtest-bucketIds=; JSESSIONID=",
  "email": "371995252@gmail.com",
  "uid": 10007109776,
  "token": "dbd7419b0c4c80455309db302b102f4fe98f"
}