{
  "vipendtime": "2025-10-29 12:00:03",
  "cookie": "user_type=0; 1&_device=iPhone&a66338b6-25bf-4f9a-b09b-23a77e5ca5e2&2.25.1; x-intl-mulehorse-bucketIds=%2C; net-mode=WIFI; channel=ios-appstore; country_id=1; idfa=01d3a6dd-b204-4ec3-a745-9bcd5a28aa1e; domain=apisg.himalaya.com; appsflyer_id=1761699600-1111111; locale=zh_CN; path=/; 1&_token=10007015587&f17acfd10433d0481e08ce30c85017f4a89e; location=sg; impl=com.ximalaya.xmlyi; x-abtest-bucketIds=; JSESSIONID=",
  "email": "145988191@gmail.com",
  "uid": 10007015587,
  "token": "f17acfd10433d0481e08ce30c85017f4a89e"
}